rolypoly/__init__.py
rolypoly/rolypoly.py
rolypoly/rpconfig.json
rolypoly/commands/__init__.py
rolypoly/commands/annotation/__init__.py
rolypoly/commands/annotation/annotate.py
rolypoly/commands/annotation/annotate_RNA.py
rolypoly/commands/annotation/annotate_prot.py
rolypoly/commands/annotation/resolve_hits.py
rolypoly/commands/assembly/__init__.py
rolypoly/commands/assembly/assemble.py
rolypoly/commands/assembly/co_assembly.py
rolypoly/commands/assembly/filter_contigs.py
rolypoly/commands/assembly/refinement.py
rolypoly/commands/bining/__init__.py
rolypoly/commands/bining/corrolate.py
rolypoly/commands/bining/termini.py
rolypoly/commands/host/__init__.py
rolypoly/commands/host/classify.py
rolypoly/commands/identify_virus/__init__.py
rolypoly/commands/identify_virus/marker_search.py
rolypoly/commands/identify_virus/rdrp_motif_search.py
rolypoly/commands/identify_virus/search_viruses.py
rolypoly/commands/reads/__init__.py
rolypoly/commands/reads/filter_reads.py
rolypoly/commands/reads/mask_dna.py
rolypoly/commands/reads/shrink_reads.py
rolypoly/commands/virotype/__init__.py
rolypoly/commands/virotype/draw_rdrp_msa.py
rolypoly/commands/virotype/predict_characteristics.py
rolypoly/commands/virotype/summarize.py
rolypoly/commands/virotype/visualize.py
rolypoly/utils/__init__.py
rolypoly/utils/lazy_group.py
rolypoly/utils/various.py
rolypoly/utils/benchmarking/__init__.py
rolypoly/utils/benchmarking/get_data.py
rolypoly/utils/bio/__init__.py
rolypoly/utils/bio/alignments.py
rolypoly/utils/bio/genome_fetch.py
rolypoly/utils/bio/interval_ops.py
rolypoly/utils/bio/library_detection.py
rolypoly/utils/bio/polars_fastx.py
rolypoly/utils/bio/sequences.py
rolypoly/utils/bio/translation.py
rolypoly/utils/bio/trees.py
rolypoly/utils/logging/__init__.py
rolypoly/utils/logging/all_used_tools_dbs_citations.json
rolypoly/utils/logging/citation_reminder.py
rolypoly/utils/logging/config.py
rolypoly/utils/logging/loggit.py
rolypoly/utils/logging/output_tracker.py
rolypoly_tk-0.6.21.dist-info/METADATA
rolypoly_tk-0.6.21.dist-info/WHEEL
rolypoly_tk-0.6.21.dist-info/entry_points.txt
rolypoly_tk-0.6.21.dist-info/licenses/LICENSE
rolypoly_tk-0.6.21.dist-info/RECORD
